{"caseNo":"case001","documentBlob":"","documentName":"14.png","errorMessage":"","results":[{"Data":{"responses":[{"fullTextAnnotation":{"pages":[{"blocks":[{"blockType":"TEXT","boundingBox":{"vertices":[{"x":233,"y":166},{"x":1049,"y":177},{"x":1046,"y":415},{"x":230,"y":404}]},"confidence":0.96125495,"paragraphs":[{"boundingBox":{"vertices":[{"x":241,"y":169},{"x":1048,"y":177},{"x":1047,"y":279},{"x":240,"y":271}]},"confidence":0.9726469,"words":[{"boundingBox":{"vertices":[{"x":241,"y":169},{"x":651,"y":173},{"x":650,"y":275},{"x":240,"y":271}]},"confidence":0.973938,"property":{"detectedLanguages":[{"confidence":1,"languageCode":"mr"}]},"symbols":[{"boundingBox":{"vertices":[{"x":241,"y":170},{"x":398,"y":172},{"x":397,"y":273},{"x":240,"y":271}]},"confidence":0.9722734,"text":"\u0906"},{"boundingBox":{"vertices":[{"x":401,"y":171},{"x":486,"y":172},{"x":485,"y":273},{"x":400,"y":272}]},"confidence":0.9718859,"text":"\u092f"},{"boundingBox":{"vertices":[{"x":482,"y":172},{"x":593,"y":173},{"x":592,"y":274},{"x":481,"y":273}]},"confidence":0.97303945,"text":"\u0915"},{"boundingBox":{"vertices":[{"x":572,"y":173},{"x":651,"y":174},{"x":650,"y":275},{"x":571,"y":274}]},"confidence":0.9785532,"property":{"detectedBreak":{"type":"SPACE"}},"text":"\u0930"}]},{"boundingBox":{"vertices":[{"x":726,"y":175},{"x":1048,"y":178},{"x":1047,"y":279},{"x":725,"y":276}]},"confidence":0.9709254,"property":{"detectedLanguages":[{"confidence":1,"languageCode":"mr"}]},"symbols":[{"boundingBox":{"vertices":[{"x":726,"y":175},{"x":858,"y":176},{"x":857,"y":277},{"x":725,"y":276}]},"confidence":0.9555935,"text":"\u0935\u093f"},{"boundingBox":{"vertices":[{"x":831,"y":176},{"x":961,"y":177},{"x":960,"y":278},{"x":830,"y":277}]},"confidence":0.9748144,"text":"\u092d\u093e"},{"boundingBox":{"vertices":[{"x":945,"y":177},{"x":1048,"y":178},{"x":1047,"y":279},{"x":944,"y":278}]},"confidence":0.9823682,"property":{"detectedBreak":{"type":"LINE_BREAK"}},"text":"\u0917"}]}]},{"boundingBox":{"vertices":[{"x":231,"y":328},{"x":1047,"y":342},{"x":1046,"y":415},{"x":230,"y":401}]},"confidence":0.9570579,"words":[{"boundingBox":{"vertices":[{"x":231,"y":328},{"x":478,"y":332},{"x":477,"y":405},{"x":230,"y":401}]},"confidence":0.9339313,"property":{"detectedLanguages":[{"confidence":1,"languageCode":"en"}]},"symbols":[{"boundingBox":{"vertices":[{"x":231,"y":329},{"x":257,"y":329},{"x":256,"y":401},{"x":230,"y":401}]},"confidence":0.9929367,"text":"I"},{"boundingBox":{"vertices":[{"x":251,"y":329},{"x":295,"y":330},{"x":294,"y":402},{"x":250,"y":401}]},"confidence":0.9905926,"text":"N"},{"boundingBox":{"vertices":[{"x":295,"y":330},{"x":340,"y":331},{"x":339,"y":403},{"x":294,"y":402}]},"confidence":0.95823276,"text":"C"},{"boundingBox":{"vertices":[{"x":334,"y":330},{"x":379,"y":331},{"x":378,"y":403},{"x":333,"y":402}]},"confidence":0.87047213,"text":"O"},{"boundingBox":{"vertices":[{"x":383,"y":331},{"x":434,"y":332},{"x":433,"y":404},{"x":382,"y":403}]},"confidence":0.8733849,"text":"M"},{"boundingBox":{"vertices":[{"x":440,"y":332},{"x":478,"y":333},{"x":477,"y":405},{"x":439,"y":404}]},"confidence":0.91796875,"property":{"detectedBreak":{"type":"SPACE"}},"text":"E"}]},{"boundingBox":{"vertices":[{"x":493,"y":332},{"x":607,"y":334},{"x":606,"y":407},{"x":492,"y":405}]},"confidence":0.9797721,"property":{"detectedLanguages":[{"confidence":1,"languageCode":"en"}]},"symbols":[{"boundingBox":{"vertices":[{"x":493,"y":333},{"x":530,"y":334},{"x":529,"y":406},{"x":492,"y":405}]},"confidence":0.98322934,"text":"T"},{"boundingBox":{"vertices":[{"x":524,"y":333},{"x":570,"y":334},{"x":569,"y":406},{"x":523,"y":405}]},"confidence":0.983377,"text":"A"},{"boundingBox":{"vertices":[{"x":566,"y":334},{"x":607,"y":335},{"x":606,"y":407},{"x":565,"y":406}]},"confidence":0.97271,"property":{"detectedBreak":{"type":"SPACE"}},"text":"X"}]},{"boundingBox":{"vertices":[{"x":627,"y":335},{"x":1047,"y":342},{"x":1046,"y":415},{"x":626,"y":408}]},"confidence":0.9641196,"property":{"detectedLanguages":[{"confidence":1,"languageCode":"en"}]},"symbols":[{"boundingBox":{"vertices":[{"x":627,"y":335},{"x":666,"y":336},{"x":665,"y":408},{"x":626,"y":407}]},"confidence":0.96313554,"text":"D"},{"boundingBox":{"vertices":[{"x":669,"y":336},{"x":704,"y":337},{"x":703,"y":409},{"x":668,"y":408}]},"confidence":0.94875914,"text":"E"},{"boundingBox":{"vertices":[{"x":711,"y":336},{"x":748,"y":337},{"x":747,"y":409},{"x":710,"y":408}]},"confidence":0.8749694,"text":"P"},{"boundingBox":{"vertices":[{"x":744,"y":337},{"x":787,"y":338},{"x":786,"y":410},{"x":743,"y":409}]},"confidence":0.94667256,"text":"A"},{"boundingBox":{"vertices":[{"x":784,"y":338},{"x":828,"y":339},{"x":827,"y":411},{"x":783,"y":410}]},"confidence":0.9697698,"text":"R"},{"boundingBox":{"vertices":[{"x":831,"y":338},{"x":872,"y":339},{"x":871,"y":411},{"x":830,"y":410}]},"confidence":0.9857599,"text":"T"},{"boundingBox":{"vertices":[{"x":871,"y":339},{"x":917,"y":340},{"x":916,"y":412},{"x":870,"y":411}]},"confidence":0.9901055,"text":"M"},{"boundingBox":{"vertices":[{"x":923,"y":340},{"x":962,"y":341},{"x":961,"y":413},{"x":922,"y":412}]},"confidence":0.9951387,"text":"E"},{"boundingBox":{"vertices":[{"x":959,"y":341},{"x":1003,"y":342},{"x":1002,"y":414},{"x":958,"y":413}]},"confidence":0.98842543,"text":"N"},{"boundingBox":{"vertices":[{"x":1007,"y":341},{"x":1047,"y":342},{"x":1046,"y":414},{"x":1006,"y":413}]},"confidence":0.9784602,"property":{"detectedBreak":{"type":"LINE_BREAK"}},"text":"T"}]}]}]},{"blockType":"TEXT","boundingBox":{"vertices":[{"x":634,"y":487},{"x":1474,"y":494},{"x":1472,"y":747},{"x":632,"y":740}]},"confidence":0.94710684,"paragraphs":[{"boundingBox":{"vertices":[{"x":634,"y":487},{"x":1474,"y":497},{"x":1472,"y":636},{"x":632,"y":626}]},"confidence":0.93604875,"words":[{"boundingBox":{"vertices":[{"x":740,"y":489},{"x":910,"y":491},{"x":909,"y":559},{"x":739,"y":557}]},"confidence":0.56785595,"property":{"detectedLanguages":[{"confidence":1,"languageCode":"hi"}]},"symbols":[{"boundingBox":{"vertices":[{"x":740,"y":489},{"x":847,"y":490},{"x":846,"y":558},{"x":739,"y":557}]},"confidence":0.35186064,"text":"\u0938\u094d\u0925\u093e"},{"boundingBox":{"vertices":[{"x":839,"y":490},{"x":910,"y":491},{"x":909,"y":559},{"x":838,"y":558}]},"confidence":0.78385127,"property":{"detectedBreak":{"type":"SPACE"}},"text":"\u092f\u0940"}]},{"boundingBox":{"vertices":[{"x":922,"y":491},{"x":1056,"y":493},{"x":1055,"y":561},{"x":921,"y":559}]},"confidence":0.8855635,"property":{"detectedLanguages":[{"confidence":1,"languageCode":"hi"}]},"symbols":[{"boundingBox":{"vertices":[{"x":922,"y":491},{"x":983,"y":492},{"x":982,"y":560},{"x":921,"y":559}]},"confidence":0.8825113,"text":"\u0932\u0947"},{"boundingBox":{"vertices":[{"x":973,"y":492},{"x":1056,"y":493},{"x":1055,"y":561},{"x":972,"y":560}]},"confidence":0.8886157,"property":{"detectedBreak":{"type":"SPACE"}},"text":"\u0916\u093e"}]},{"boundingBox":{"vertices":[{"x":1078,"y":493},{"x":1225,"y":495},{"x":1224,"y":563},{"x":1077,"y":561}]},"confidence":0.93069804,"property":{"detectedLanguages":[{"confidence":1,"languageCode":"hi"}]},"symbols":[{"boundingBox":{"vertices":[{"x":1078,"y":493},{"x":1129,"y":494},{"x":1128,"y":562},{"x":1077,"y":561}]},"confidence":0.95928454,"text":"\u0938\u0902"},{"boundingBox":{"vertices":[{"x":1115,"y":493},{"x":1225,"y":494},{"x":1224,"y":562},{"x":1114,"y":561}]},"confidence":0.9021115,"property":{"detectedBreak":{"type":"SPACE"}},"text":"\u0916\u094d\u092f\u093e"}]},{"boundingBox":{"vertices":[{"x":1243,"y":495},{"x":1365,"y":497},{"x":1364,"y":565},{"x":1242,"y":563}]},"confidence":0.92748487,"property":{"detectedLanguages":[{"confidence":1,"languageCode":"hi"}]},"symbols":[{"boundingBox":{"vertices":[{"x":1243,"y":495},{"x":1328,"y":496},{"x":1327,"y":564},{"x":1242,"y":563}]},"confidence":0.934461,"text":"\u0915\u093e"},{"boundingBox":{"vertices":[{"x":1322,"y":496},{"x":1365,"y":497},{"x":1364,"y":565},{"x":1321,"y":564}]},"confidence":0.92050874,"property":{"detectedBreak":{"type":"EOL_SURE_SPACE"}},"text":"\u0930\u094d\u0921"}]},{"boundingBox":{"vertices":[{"x":633,"y":576},{"x":909,"y":579},{"x":909,"y":629},{"x":633,"y":626}]},"confidence":0.971745,"property":{"detectedLanguages":[{"confidence":1,"languageCode":"en"}]},"symbols":[{"boundingBox":{"vertices":[{"x":633,"y":577},{"x":665,"y":577},{"x":665,"y":626},{"x":633,"y":626}]},"confidence":0.96975875,"text":"P"},{"boundingBox":{"vertices":[{"x":669,"y":577},{"x":696,"y":577},{"x":696,"y":626},{"x":669,"y":626}]},"confidence":0.95941144,"text":"e"},{"boundingBox":{"vertices":[{"x":696,"y":577},{"x":724,"y":577},{"x":724,"y":626},{"x":696,"y":626}]},"confidence":0.9722273,"text":"r"},{"boundingBox":{"vertices":[{"x":713,"y":577},{"x":756,"y":577},{"x":756,"y":626},{"x":713,"y":626}]},"confidence":0.95297337,"text":"m"},{"boundingBox":{"vertices":[{"x":763,"y":578},{"x":791,"y":578},{"x":791,"y":627},{"x":763,"y":627}]},"confidence":0.95636,"text":"a"},{"boundingBox":{"vertices":[{"x":793,"y":578},{"x":820,"y":578},{"x":820,"y":627},{"x":793,"y":627}]},"confidence":0.96473956,"text":"n"},{"boundingBox":{"vertices":[{"x":825,"y":578},{"x":854,"y":578},{"x":854,"y":627},{"x":825,"y":627}]},"confidence":0.991197,"text":"e"},{"boundingBox":{"vertices":[{"x":853,"y":579},{"x":883,"y":579},{"x":883,"y":628},{"x":853,"y":628}]},"confidence":0.9860227,"text":"n"},{"boundingBox":{"vertices":[{"x":886,"y":579},{"x":909,"y":579},{"x":909,"y":628},{"x":886,"y":628}]},"confidence":0.993015,"property":{"detectedBreak":{"type":"SPACE"}},"text":"t"}]},{"boundingBox":{"vertices":[{"x":917,"y":579},{"x":1129,"y":581},{"x":1129,"y":631},{"x":917,"y":629}]},"confidence":0.9825892,"property":{"detectedLanguages":[{"confidence":1,"languageCode":"en"}]},"symbols":[{"boundingBox":{"vertices":[{"x":917,"y":579},{"x":956,"y":579},{"x":956,"y":628},{"x":917,"y":628}]},"confidence":0.9832586,"text":"A"},{"boundingBox":{"vertices":[{"x":954,"y":580},{"x":989,"y":580},{"x":989,"y":629},{"x":954,"y":629}]},"confidence":0.98286617,"text":"c"},{"boundingBox":{"vertices":[{"x":985,"y":580},{"x":1021,"y":580},{"x":1021,"y":629},{"x":985,"y":629}]},"confidence":0.98447376,"text":"c"},{"boundingBox":{"vertices":[{"x":1013,"y":580},{"x":1051,"y":580},{"x":1051,"y":629},{"x":1013,"y":629}]},"confidence":0.9729189,"text":"o"},{"boundingBox":{"vertices":[{"x":1043,"y":580},{"x":1078,"y":580},{"x":1078,"y":629},{"x":1043,"y":629}]},"confidence":0.9888425,"text":"u"},{"boundingBox":{"vertices":[{"x":1075,"y":581},{"x":1111,"y":581},{"x":1111,"y":630},{"x":1075,"y":630}]},"confidence":0.9834658,"text":"n"},{"boundingBox":{"vertices":[{"x":1107,"y":581},{"x":1129,"y":581},{"x":1129,"y":630},{"x":1107,"y":630}]},"confidence":0.98229843,"property":{"detectedBreak":{"type":"SPACE"}},"text":"t"}]},{"boundingBox":{"vertices":[{"x":1141,"y":581},{"x":1342,"y":583},{"x":1342,"y":633},{"x":1141,"y":631}]},"confidence":0.99094665,"property":{"detectedLanguages":[{"confidence":1,"languageCode":"en"}]},"symbols":[{"boundingBox":{"vertices":[{"x":1141,"y":581},{"x":1176,"y":581},{"x":1176,"y":630},{"x":1141,"y":630}]},"confidence":0.9900891,"text":"N"},{"boundingBox":{"vertices":[{"x":1179,"y":582},{"x":1208,"y":582},{"x":1208,"y":631},{"x":1179,"y":631}]},"confidence":0.977756,"text":"u"},{"boundingBox":{"vertices":[{"x":1211,"y":582},{"x":1254,"y":582},{"x":1254,"y":631},{"x":1211,"y":631}]},"confidence":0.9959588,"text":"m"},{"boundingBox":{"vertices":[{"x":1255,"y":583},{"x":1288,"y":583},{"x":1288,"y":632},{"x":1255,"y":632}]},"confidence":0.99447787,"text":"b"},{"boundingBox":{"vertices":[{"x":1287,"y":583},{"x":1317,"y":583},{"x":1317,"y":632},{"x":1287,"y":632}]},"confidence":0.9959107,"text":"e"},{"boundingBox":{"vertices":[{"x":1319,"y":583},{"x":1342,"y":583},{"x":1342,"y":632},{"x":1319,"y":632}]},"confidence":0.99148744,"property":{"detectedBreak":{"type":"SPACE"}},"text":"r"}]},{"boundingBox":{"vertices":[{"x":1353,"y":583},{"x":1473,"y":584},{"x":1473,"y":634},{"x":1353,"y":633}]},"confidence":0.9082359,"property":{"detectedLanguages":[{"confidence":1,"languageCode":"en"}]},"symbols":[{"boundingBox":{"vertices":[{"x":1353,"y":583},{"x":1387,"y":583},{"x":1387,"y":632},{"x":1353,"y":632}]},"confidence":0.96619403,"text":"C"},{"boundingBox":{"vertices":[{"x":1389,"y":584},{"x":1420,"y":584},{"x":1420,"y":633},{"x":1389,"y":633}]},"confidence":0.9486786,"text":"a"},{"boundingBox":{"vertices":[{"x":1421,"y":584},{"x":1450,"y":584},{"x":1450,"y":633},{"x":1421,"y":633}]},"confidence":0.8331668,"text":"r"},{"boundingBox":{"vertices":[{"x":1436,"y":584},{"x":1473,"y":584},{"x":1473,"y":633},{"x":1436,"y":633}]},"confidence":0.8849042,"property":{"detectedBreak":{"type":"LINE_BREAK"}},"text":"d"}]}]},{"boundingBox":{"vertices":[{"x":842,"y":686},{"x":1324,"y":689},{"x":1324,"y":745},{"x":842,"y":742}]},"confidence":0.98470443,"words":[{"boundingBox":{"vertices":[{"x":842,"y":686},{"x":1324,"y":689},{"x":1324,"y":745},{"x":842,"y":742}]},"confidence":0.98470443,"property":{"detectedLanguages":[{"confidence":1,"languageCode":"en"}]},"symbols":[{"boundingBox":{"vertices":[{"x":842,"y":687},{"x":890,"y":687},{"x":890,"y":742},{"x":842,"y":742}]},"confidence":0.99395573,"text":"E"},{"boundingBox":{"vertices":[{"x":888,"y":687},{"x":938,"y":687},{"x":938,"y":742},{"x":888,"y":742}]},"confidence":0.9938501,"text":"X"},{"boundingBox":{"vertices":[{"x":941,"y":687},{"x":987,"y":687},{"x":987,"y":742},{"x":941,"y":742}]},"confidence":0.99129736,"text":"H"},{"boundingBox":{"vertices":[{"x":997,"y":687},{"x":1042,"y":687},{"x":1042,"y":742},{"x":997,"y":742}]},"confidence":0.99258447,"text":"P"},{"boundingBox":{"vertices":[{"x":1048,"y":688},{"x":1096,"y":688},{"x":1096,"y":743},{"x":1048,"y":743}]},"confidence":0.9937612,"text":"D"},{"boundingBox":{"vertices":[{"x":1100,"y":688},{"x":1141,"y":688},{"x":1141,"y":743},{"x":1100,"y":743}]},"confidence":0.98830956,"text":"6"},{"boundingBox":{"vertices":[{"x":1145,"y":688},{"x":1182,"y":688},{"x":1182,"y":743},{"x":1145,"y":743}]},"confidence":0.986848,"text":"8"},{"boundingBox":{"vertices":[{"x":1180,"y":689},{"x":1224,"y":689},{"x":1224,"y":744},{"x":1180,"y":744}]},"confidence":0.98163414,"text":"4"},{"boundingBox":{"vertices":[{"x":1226,"y":689},{"x":1271,"y":689},{"x":1271,"y":744},{"x":1226,"y":744}]},"confidence":0.9891834,"text":"6"},{"boundingBox":{"vertices":[{"x":1273,"y":689},{"x":1324,"y":689},{"x":1324,"y":744},{"x":1273,"y":744}]},"confidence":0.93562037,"property":{"detectedBreak":{"type":"LINE_BREAK"}},"text":"P"}]}]}]},{"blockType":"TEXT","boundingBox":{"vertices":[{"x":205,"y":825},{"x":468,"y":828},{"x":468,"y":874},{"x":205,"y":871}]},"confidence":0.60046476,"paragraphs":[{"boundingBox":{"vertices":[{"x":205,"y":825},{"x":468,"y":828},{"x":468,"y":874},{"x":205,"y":871}]},"confidence":0.60046476,"words":[{"boundingBox":{"vertices":[{"x":205,"y":825},{"x":313,"y":826},{"x":313,"y":872},{"x":205,"y":871}]},"confidence":0.29851505,"property":{"detectedLanguages":[{"confidence":1,"languageCode":"en"}]},"symbols":[{"boundingBox":{"vertices":[{"x":205,"y":826},{"x":244,"y":826},{"x":244,"y":871},{"x":205,"y":871}]},"confidence":0.30000106,"text":"R"},{"boundingBox":{"vertices":[{"x":211,"y":826},{"x":246,"y":826},{"x":246,"y":871},{"x":211,"y":871}]},"confidence":0.27684018,"text":"a"},{"boundingBox":{"vertices":[{"x":244,"y":826},{"x":287,"y":826},{"x":287,"y":871},{"x":244,"y":871}]},"confidence":0.32490036,"text":"n"},{"boundingBox":{"vertices":[{"x":274,"y":826},{"x":313,"y":826},{"x":313,"y":871},{"x":274,"y":871}]},"confidence":0.29231864,"property":{"detectedBreak":{"type":"SPACE"}},"text":"t"}]},{"boundingBox":{"vertices":[{"x":306,"y":827},{"x":338,"y":827},{"x":338,"y":872},{"x":306,"y":872}]},"confidence":0.4351672,"property":{"detectedLanguages":[{"confidence":1,"languageCode":"en"}]},"symbols":[{"boundingBox":{"vertices":[{"x":306,"y":827},{"x":338,"y":827},{"x":338,"y":872},{"x":306,"y":872}]},"confidence":0.4351672,"property":{"detectedBreak":{"type":"SPACE"}},"text":"/"}]},{"boundingBox":{"vertices":[{"x":337,"y":826},{"x":468,"y":827},{"x":468,"y":873},{"x":337,"y":872}]},"confidence":0.9437388,"property":{"detectedLanguages":[{"confidence":1,"languageCode":"en"}]},"symbols":[{"boundingBox":{"vertices":[{"x":337,"y":827},{"x":379,"y":827},{"x":379,"y":872},{"x":337,"y":872}]},"confidence":0.88477296,"text":"N"},{"boundingBox":{"vertices":[{"x":374,"y":827},{"x":407,"y":827},{"x":407,"y":872},{"x":374,"y":872}]},"confidence":0.94673246,"text":"a"},{"boundingBox":{"vertices":[{"x":399,"y":827},{"x":446,"y":827},{"x":446,"y":872},{"x":399,"y":872}]},"confidence":0.96160936,"text":"m"},{"boundingBox":{"vertices":[{"x":438,"y":828},{"x":468,"y":828},{"x":468,"y":873},{"x":438,"y":873}]},"confidence":0.98184055,"property":{"detectedBreak":{"type":"LINE_BREAK"}},"text":"e"}]}]}]},{"blockType":"TEXT","boundingBox":{"vertices":[{"x":222,"y":895},{"x":821,"y":900},{"x":821,"y":946},{"x":222,"y":941}]},"confidence":0.9893526,"paragraphs":[{"boundingBox":{"vertices":[{"x":222,"y":895},{"x":821,"y":900},{"x":821,"y":946},{"x":222,"y":941}]},"confidence":0.9893526,"words":[{"boundingBox":{"vertices":[{"x":222,"y":895},{"x":528,"y":898},{"x":528,"y":944},{"x":222,"y":941}]},"confidence":0.99203026,"symbols":[{"boundingBox":{"vertices":[{"x":222,"y":896},{"x":261,"y":896},{"x":261,"y":941},{"x":222,"y":941}]},"confidence":0.9896597,"text":"D"},{"boundingBox":{"vertices":[{"x":263,"y":896},{"x":285,"y":896},{"x":285,"y":941},{"x":263,"y":941}]},"confidence":0.99002516,"text":"I"},{"boundingBox":{"vertices":[{"x":284,"y":896},{"x":324,"y":896},{"x":324,"y":941},{"x":284,"y":941}]},"confidence":0.9948967,"text":"P"},{"boundingBox":{"vertices":[{"x":318,"y":896},{"x":362,"y":896},{"x":362,"y":941},{"x":318,"y":941}]},"confidence":0.9929373,"text":"A"},{"boundingBox":{"vertices":[{"x":354,"y":897},{"x":398,"y":897},{"x":398,"y":942},{"x":354,"y":942}]},"confidence":0.9922944,"text":"N"},{"boundingBox":{"vertices":[{"x":403,"y":897},{"x":444,"y":897},{"x":444,"y":942},{"x":403,"y":942}]},"confidence":0.9935148,"text":"K"},{"boundingBox":{"vertices":[{"x":444,"y":898},{"x":486,"y":898},{"x":486,"y":943},{"x":444,"y":943}]},"confidence":0.9925577,"text":"A"},{"boundingBox":{"vertices":[{"x":489,"y":898},{"x":528,"y":898},{"x":528,"y":943},{"x":489,"y":943}]},"confidence":0.99035645,"property":{"detectedBreak":{"type":"SPACE"}},"text":"R"}]},{"boundingBox":{"vertices":[{"x":548,"y":898},{"x":821,"y":900},{"x":821,"y":946},{"x":548,"y":944}]},"confidence":0.9862923,"symbols":[{"boundingBox":{"vertices":[{"x":548,"y":898},{"x":586,"y":898},{"x":586,"y":943},{"x":548,"y":943}]},"confidence":0.97802085,"text":"D"},{"boundingBox":{"vertices":[{"x":588,"y":899},{"x":627,"y":899},{"x":627,"y":944},{"x":588,"y":944}]},"confidence":0.99042726,"text":"H"},{"boundingBox":{"vertices":[{"x":631,"y":899},{"x":674,"y":899},{"x":674,"y":944},{"x":631,"y":944}]},"confidence":0.9904073,"text":"A"},{"boundingBox":{"vertices":[{"x":675,"y":900},{"x":714,"y":900},{"x":714,"y":945},{"x":675,"y":945}]},"confidence":0.99238515,"text":"U"},{"boundingBox":{"vertices":[{"x":716,"y":900},{"x":757,"y":900},{"x":757,"y":945},{"x":716,"y":945}]},"confidence":0.9909486,"text":"R"},{"boundingBox":{"vertices":[{"x":759,"y":900},{"x":780,"y":900},{"x":780,"y":945},{"x":759,"y":945}]},"confidence":0.9867038,"text":"I"},{"boundingBox":{"vertices":[{"x":778,"y":901},{"x":821,"y":901},{"x":821,"y":946},{"x":778,"y":946}]},"confidence":0.97515315,"property":{"detectedBreak":{"type":"LINE_BREAK"}},"text":"A"}]}]}]},{"blockType":"TEXT","boundingBox":{"vertices":[{"x":206,"y":1044},{"x":849,"y":1053},{"x":847,"y":1173},{"x":204,"y":1164}]},"confidence":0.9191776,"paragraphs":[{"boundingBox":{"vertices":[{"x":206,"y":1044},{"x":849,"y":1053},{"x":847,"y":1173},{"x":204,"y":1164}]},"confidence":0.9191776,"words":[{"boundingBox":{"vertices":[{"x":206,"y":1044},{"x":301,"y":1046},{"x":300,"y":1096},{"x":205,"y":1094}]},"confidence":0.7224425,"property":{"detectedLanguages":[{"confidence":1,"languageCode":"hi"}]},"symbols":[{"boundingBox":{"vertices":[{"x":206,"y":1045},{"x":260,"y":1046},{"x":259,"y":1095},{"x":205,"y":1094}]},"confidence":0.7178076,"text":"\u092a\u093f"},{"boundingBox":{"vertices":[{"x":250,"y":1045},{"x":301,"y":1046},{"x":300,"y":1095},{"x":249,"y":1094}]},"confidence":0.7270774,"property":{"detectedBreak":{"type":"SPACE"}},"text":"\u0924\u093e"}]},{"boundingBox":{"vertices":[{"x":314,"y":1046},{"x":371,"y":1047},{"x":370,"y":1096},{"x":313,"y":1095}]},"confidence":0.65567946,"property":{"detectedLanguages":[{"confidence":1,"languageCode":"hi"}]},"symbols":[{"boundingBox":{"vertices":[{"x":314,"y":1046},{"x":371,"y":1047},{"x":370,"y":1096},{"x":313,"y":1095}]},"confidence":0.65567946,"property":{"detectedBreak":{"type":"SPACE"}},"text":"\u0915\u093e"}]},{"boundingBox":{"vertices":[{"x":391,"y":1048},{"x":469,"y":1049},{"x":468,"y":1098},{"x":390,"y":1097}]},"confidence":0.67934215,"property":{"detectedLanguages":[{"confidence":1,"languageCode":"hi"}]},"symbols":[{"boundingBox":{"vertices":[{"x":391,"y":1048},{"x":439,"y":1049},{"x":438,"y":1098},{"x":390,"y":1097}]},"confidence":0.6165585,"text":"\u0928\u093e"},{"boundingBox":{"vertices":[{"x":438,"y":1049},{"x":469,"y":1050},{"x":468,"y":1099},{"x":437,"y":1098}]},"confidence":0.7421258,"property":{"detectedBreak":{"type":"SPACE"}},"text":"\u092e"}]},{"boundingBox":{"vertices":[{"x":504,"y":1050},{"x":510,"y":1050},{"x":509,"y":1099},{"x":503,"y":1099}]},"confidence":0.6043228,"property":{"detectedLanguages":[{"confidence":1,"languageCode":"hi"}]},"symbols":[{"boundingBox":{"vertices":[{"x":504,"y":1050},{"x":510,"y":1050},{"x":509,"y":1099},{"x":503,"y":1099}]},"confidence":0.6043228,"property":{"detectedBreak":{"type":"SPACE"}},"text":"|"}]},{"boundingBox":{"vertices":[{"x":527,"y":1050},{"x":699,"y":1053},{"x":698,"y":1103},{"x":526,"y":1100}]},"confidence":0.974407,"property":{"detectedLanguages":[{"confidence":1,"languageCode":"hi"}]},"symbols":[{"boundingBox":{"vertices":[{"x":527,"y":1050},{"x":551,"y":1050},{"x":550,"y":1099},{"x":526,"y":1099}]},"confidence":0.9533069,"text":"F"},{"boundingBox":{"vertices":[{"x":555,"y":1051},{"x":576,"y":1051},{"x":575,"y":1100},{"x":554,"y":1100}]},"confidence":0.9835092,"text":"a"},{"boundingBox":{"vertices":[{"x":581,"y":1051},{"x":594,"y":1051},{"x":593,"y":1100},{"x":580,"y":1100}]},"confidence":0.99348915,"text":"t"},{"boundingBox":{"vertices":[{"x":596,"y":1051},{"x":618,"y":1051},{"x":617,"y":1100},{"x":595,"y":1100}]},"confidence":0.99278027,"text":"h"},{"boundingBox":{"vertices":[{"x":624,"y":1052},{"x":649,"y":1052},{"x":648,"y":1101},{"x":623,"y":1101}]},"confidence":0.985384,"text":"e"},{"boundingBox":{"vertices":[{"x":650,"y":1052},{"x":677,"y":1052},{"x":676,"y":1101},{"x":649,"y":1101}]},"confidence":0.97197,"text":"r"},{"boundingBox":{"vertices":[{"x":653,"y":1052},{"x":674,"y":1052},{"x":673,"y":1101},{"x":652,"y":1101}]},"confidence":0.9440826,"text":"'"},{"boundingBox":{"vertices":[{"x":671,"y":1053},{"x":699,"y":1053},{"x":698,"y":1102},{"x":670,"y":1102}]},"confidence":0.9707339,"property":{"detectedBreak":{"type":"SPACE"}},"text":"s"}]},{"boundingBox":{"vertices":[{"x":719,"y":1053},{"x":836,"y":1055},{"x":835,"y":1104},{"x":718,"y":1102}]},"confidence":0.98376834,"property":{"detectedLanguages":[{"confidence":1,"languageCode":"hi"}]},"symbols":[{"boundingBox":{"vertices":[{"x":719,"y":1053},{"x":749,"y":1054},{"x":748,"y":1103},{"x":718,"y":1102}]},"confidence":0.985344,"text":"N"},{"boundingBox":{"vertices":[{"x":748,"y":1054},{"x":773,"y":1054},{"x":772,"y":1103},{"x":747,"y":1103}]},"confidence":0.984018,"text":"a"},{"boundingBox":{"vertices":[{"x":776,"y":1054},{"x":816,"y":1055},{"x":815,"y":1104},{"x":775,"y":1103}]},"confidence":0.984083,"text":"m"},{"boundingBox":{"vertices":[{"x":815,"y":1055},{"x":836,"y":1055},{"x":835,"y":1104},{"x":814,"y":1104}]},"confidence":0.9816285,"property":{"detectedBreak":{"type":"EOL_SURE_SPACE"}},"text":"e"}]},{"boundingBox":{"vertices":[{"x":217,"y":1120},{"x":550,"y":1123},{"x":550,"y":1167},{"x":217,"y":1164}]},"confidence":0.96541655,"symbols":[{"boundingBox":{"vertices":[{"x":217,"y":1121},{"x":252,"y":1121},{"x":252,"y":1164},{"x":217,"y":1164}]},"confidence":0.97876436,"text":"P"},{"boundingBox":{"vertices":[{"x":255,"y":1121},{"x":296,"y":1121},{"x":296,"y":1164},{"x":255,"y":1164}]},"confidence":0.96281254,"text":"U"},{"boundingBox":{"vertices":[{"x":299,"y":1121},{"x":340,"y":1121},{"x":340,"y":1164},{"x":299,"y":1164}]},"confidence":0.96425617,"text":"R"},{"boundingBox":{"vertices":[{"x":341,"y":1122},{"x":381,"y":1122},{"x":381,"y":1165},{"x":341,"y":1165}]},"confidence":0.9598733,"text":"N"},{"boundingBox":{"vertices":[{"x":385,"y":1122},{"x":424,"y":1122},{"x":424,"y":1165},{"x":385,"y":1165}]},"confidence":0.9581945,"text":"E"},{"boundingBox":{"vertices":[{"x":423,"y":1122},{"x":463,"y":1122},{"x":463,"y":1165},{"x":423,"y":1165}]},"confidence":0.97653425,"text":"N"},{"boundingBox":{"vertices":[{"x":466,"y":1123},{"x":506,"y":1123},{"x":506,"y":1166},{"x":466,"y":1166}]},"confidence":0.9623998,"text":"D"},{"boundingBox":{"vertices":[{"x":509,"y":1123},{"x":550,"y":1123},{"x":550,"y":1166},{"x":509,"y":1166}]},"confidence":0.96049756,"property":{"detectedBreak":{"type":"SPACE"}},"text":"U"}]},{"boundingBox":{"vertices":[{"x":571,"y":1123},{"x":848,"y":1126},{"x":848,"y":1170},{"x":571,"y":1167}]},"confidence":0.97366107,"symbols":[{"boundingBox":{"vertices":[{"x":571,"y":1124},{"x":611,"y":1124},{"x":611,"y":1167},{"x":571,"y":1167}]},"confidence":0.9430893,"text":"D"},{"boundingBox":{"vertices":[{"x":612,"y":1124},{"x":651,"y":1124},{"x":651,"y":1167},{"x":612,"y":1167}]},"confidence":0.95873225,"text":"H"},{"boundingBox":{"vertices":[{"x":653,"y":1125},{"x":701,"y":1125},{"x":701,"y":1168},{"x":653,"y":1168}]},"confidence":0.9810634,"text":"A"},{"boundingBox":{"vertices":[{"x":697,"y":1125},{"x":738,"y":1125},{"x":738,"y":1168},{"x":697,"y":1168}]},"confidence":0.9846219,"text":"U"},{"boundingBox":{"vertices":[{"x":740,"y":1125},{"x":783,"y":1125},{"x":783,"y":1168},{"x":740,"y":1168}]},"confidence":0.9925786,"text":"R"},{"boundingBox":{"vertices":[{"x":783,"y":1126},{"x":808,"y":1126},{"x":808,"y":1169},{"x":783,"y":1169}]},"confidence":0.9820067,"text":"I"},{"boundingBox":{"vertices":[{"x":802,"y":1126},{"x":848,"y":1126},{"x":848,"y":1169},{"x":802,"y":1169}]},"confidence":0.97353506,"property":{"detectedBreak":{"type":"LINE_BREAK"}},"text":"A"}]}]}]},{"blockType":"TEXT","boundingBox":{"vertices":[{"x":185,"y":1302},{"x":730,"y":1308},{"x":728,"y":1449},{"x":183,"y":1443}]},"confidence":0.7887903,"paragraphs":[{"boundingBox":{"vertices":[{"x":185,"y":1302},{"x":730,"y":1308},{"x":728,"y":1449},{"x":183,"y":1443}]},"confidence":0.7887903,"words":[{"boundingBox":{"vertices":[{"x":186,"y":1303},{"x":287,"y":1305},{"x":286,"y":1358},{"x":185,"y":1356}]},"confidence":0.4677226,"property":{"detectedLanguages":[{"confidence":1,"languageCode":"hi"}]},"symbols":[{"boundingBox":{"vertices":[{"x":186,"y":1303},{"x":247,"y":1304},{"x":246,"y":1357},{"x":185,"y":1356}]},"confidence":0.59911674,"text":"\u091c"},{"boundingBox":{"vertices":[{"x":232,"y":1304},{"x":287,"y":1305},{"x":286,"y":1358},{"x":231,"y":1357}]},"confidence":0.33632842,"property":{"detectedBreak":{"type":"SPACE"}},"text":"\u0928\u094d\u092e"}]},{"boundingBox":{"vertices":[{"x":299,"y":1305},{"x":363,"y":1306},{"x":362,"y":1359},{"x":298,"y":1358}]},"confidence":0.7346499,"property":{"detectedLanguages":[{"confidence":1,"languageCode":"hi"}]},"symbols":[{"boundingBox":{"vertices":[{"x":299,"y":1305},{"x":363,"y":1306},{"x":362,"y":1359},{"x":298,"y":1358}]},"confidence":0.7346499,"property":{"detectedBreak":{"type":"SPACE"}},"text":"\u0915\u0940"}]},{"boundingBox":{"vertices":[{"x":376,"y":1307},{"x":508,"y":1310},{"x":507,"y":1363},{"x":375,"y":1360}]},"confidence":0.7302915,"property":{"detectedLanguages":[{"confidence":1,"languageCode":"hi"}]},"symbols":[{"boundingBox":{"vertices":[{"x":376,"y":1307},{"x":427,"y":1308},{"x":426,"y":1361},{"x":375,"y":1360}]},"confidence":0.7817406,"text":"\u0924\u093e"},{"boundingBox":{"vertices":[{"x":421,"y":1308},{"x":461,"y":1309},{"x":460,"y":1362},{"x":420,"y":1361}]},"confidence":0.8294353,"text":"\u0930\u0940"},{"boundingBox":{"vertices":[{"x":462,"y":1309},{"x":508,"y":1310},{"x":507,"y":1363},{"x":461,"y":1362}]},"confidence":0.5796985,"property":{"detectedBreak":{"type":"SPACE"}},"text":"\u0916"}]},{"boundingBox":{"vertices":[{"x":533,"y":1310},{"x":545,"y":1310},{"x":544,"y":1363},{"x":532,"y":1363}]},"confidence":0.49029762,"property":{"detectedLanguages":[{"confidence":1,"languageCode":"hi"}]},"symbols":[{"boundingBox":{"vertices":[{"x":533,"y":1310},{"x":545,"y":1310},{"x":544,"y":1363},{"x":532,"y":1363}]},"confidence":0.49029762,"property":{"detectedBreak":{"type":"SPACE"}},"text":"/"}]},{"boundingBox":{"vertices":[{"x":557,"y":1310},{"x":665,"y":1312},{"x":664,"y":1366},{"x":556,"y":1364}]},"confidence":0.5947426,"property":{"detectedLanguages":[{"confidence":1,"languageCode":"hi"}]},"symbols":[{"boundingBox":{"vertices":[{"x":557,"y":1311},{"x":588,"y":1312},{"x":587,"y":1365},{"x":556,"y":1364}]},"confidence":0.424136,"text":"D"},{"boundingBox":{"vertices":[{"x":589,"y":1311},{"x":622,"y":1312},{"x":621,"y":1365},{"x":588,"y":1364}]},"confidence":0.6923273,"text":"a"},{"boundingBox":{"vertices":[{"x":608,"y":1312},{"x":639,"y":1313},{"x":638,"y":1366},{"x":607,"y":1365}]},"confidence":0.65556616,"text":"t"},{"boundingBox":{"vertices":[{"x":624,"y":1312},{"x":665,"y":1313},{"x":664,"y":1366},{"x":623,"y":1365}]},"confidence":0.606941,"property":{"detectedBreak":{"type":"SPACE"}},"text":"e"}]},{"boundingBox":{"vertices":[{"x":652,"y":1313},{"x":730,"y":1315},{"x":729,"y":1368},{"x":651,"y":1366}]},"confidence":0.79546213,"property":{"detectedLanguages":[{"confidence":1,"languageCode":"hi"}]},"symbols":[{"boundingBox":{"vertices":[{"x":652,"y":1313},{"x":706,"y":1314},{"x":705,"y":1367},{"x":651,"y":1366}]},"confidence":0.7778749,"text":"o"},{"boundingBox":{"vertices":[{"x":696,"y":1314},{"x":730,"y":1315},{"x":729,"y":1368},{"x":695,"y":1367}]},"confidence":0.81304944,"property":{"detectedBreak":{"type":"EOL_SURE_SPACE"}},"text":"f"}]},{"boundingBox":{"vertices":[{"x":202,"y":1387},{"x":594,"y":1387},{"x":594,"y":1443},{"x":202,"y":1443}]},"confidence":0.9821015,"symbols":[{"boundingBox":{"vertices":[{"x":202,"y":1387},{"x":241,"y":1387},{"x":241,"y":1443},{"x":202,"y":1443}]},"confidence":0.97290885,"text":"2"},{"boundingBox":{"vertices":[{"x":247,"y":1387},{"x":286,"y":1387},{"x":286,"y":1443},{"x":247,"y":1443}]},"confidence":0.97476315,"text":"7"},{"boundingBox":{"vertices":[{"x":287,"y":1387},{"x":318,"y":1387},{"x":318,"y":1443},{"x":287,"y":1443}]},"confidence":0.9797968,"text":"/"},{"boundingBox":{"vertices":[{"x":318,"y":1387},{"x":352,"y":1387},{"x":352,"y":1443},{"x":318,"y":1443}]},"confidence":0.98841673,"text":"1"},{"boundingBox":{"vertices":[{"x":357,"y":1387},{"x":390,"y":1387},{"x":390,"y":1443},{"x":357,"y":1443}]},"confidence":0.98224586,"text":"1"},{"boundingBox":{"vertices":[{"x":394,"y":1387},{"x":428,"y":1387},{"x":428,"y":1443},{"x":394,"y":1443}]},"confidence":0.975664,"text":"/"},{"boundingBox":{"vertices":[{"x":424,"y":1387},{"x":456,"y":1387},{"x":456,"y":1443},{"x":424,"y":1443}]},"confidence":0.9830324,"text":"1"},{"boundingBox":{"vertices":[{"x":463,"y":1387},{"x":503,"y":1387},{"x":503,"y":1443},{"x":463,"y":1443}]},"confidence":0.98648626,"text":"9"},{"boundingBox":{"vertices":[{"x":509,"y":1387},{"x":549,"y":1387},{"x":549,"y":1443},{"x":509,"y":1443}]},"confidence":0.98934114,"text":"9"},{"boundingBox":{"vertices":[{"x":554,"y":1387},{"x":594,"y":1387},{"x":594,"y":1443},{"x":554,"y":1443}]},"confidence":0.98835963,"property":{"detectedBreak":{"type":"LINE_BREAK"}},"text":"6"}]}]}]},{"blockType":"TEXT","boundingBox":{"vertices":[{"x":1125,"y":1400},{"x":1433,"y":1410},{"x":1431,"y":1454},{"x":1124,"y":1444}]},"confidence":0.6551755,"paragraphs":[{"boundingBox":{"vertices":[{"x":1125,"y":1400},{"x":1433,"y":1410},{"x":1431,"y":1454},{"x":1124,"y":1444}]},"confidence":0.6551755,"words":[{"boundingBox":{"vertices":[{"x":1125,"y":1401},{"x":1199,"y":1403},{"x":1198,"y":1446},{"x":1124,"y":1444}]},"confidence":0.35645965,"property":{"detectedLanguages":[{"confidence":1,"languageCode":"la"}]},"symbols":[{"boundingBox":{"vertices":[{"x":1125,"y":1401},{"x":1166,"y":1402},{"x":1165,"y":1445},{"x":1124,"y":1444}]},"confidence":0.30872163,"text":"E"},{"boundingBox":{"vertices":[{"x":1166,"y":1402},{"x":1199,"y":1403},{"x":1198,"y":1446},{"x":1165,"y":1445}]},"confidence":0.40419766,"text":"T"}]},{"boundingBox":{"vertices":[{"x":1212,"y":1403},{"x":1239,"y":1404},{"x":1238,"y":1447},{"x":1211,"y":1446}]},"confidence":0.58546805,"property":{"detectedLanguages":[{"confidence":1,"languageCode":"la"}]},"symbols":[{"boundingBox":{"vertices":[{"x":1212,"y":1403},{"x":1239,"y":1404},{"x":1238,"y":1447},{"x":1211,"y":1446}]},"confidence":0.58546805,"text":"/"}]},{"boundingBox":{"vertices":[{"x":1233,"y":1404},{"x":1433,"y":1411},{"x":1431,"y":1454},{"x":1232,"y":1447}]},"confidence":0.7385679,"property":{"detectedLanguages":[{"confidence":1,"languageCode":"la"}]},"symbols":[{"boundingBox":{"vertices":[{"x":1233,"y":1404},{"x":1273,"y":1405},{"x":1272,"y":1448},{"x":1232,"y":1447}]},"confidence":0.8412662,"text":"S"},{"boundingBox":{"vertices":[{"x":1269,"y":1405},{"x":1288,"y":1406},{"x":1287,"y":1449},{"x":1268,"y":1448}]},"confidence":0.8297114,"text":"i"},{"boundingBox":{"vertices":[{"x":1281,"y":1406},{"x":1313,"y":1407},{"x":1312,"y":1450},{"x":1280,"y":1449}]},"confidence":0.8339517,"text":"g"},{"boundingBox":{"vertices":[{"x":1311,"y":1407},{"x":1336,"y":1408},{"x":1335,"y":1451},{"x":1310,"y":1450}]},"confidence":0.77802354,"text":"n"},{"boundingBox":{"vertices":[{"x":1338,"y":1407},{"x":1364,"y":1408},{"x":1363,"y":1451},{"x":1337,"y":1450}]},"confidence":0.7362273,"text":"a"},{"boundingBox":{"vertices":[{"x":1361,"y":1408},{"x":1386,"y":1409},{"x":1385,"y":1452},{"x":1360,"y":1451}]},"confidence":0.762172,"text":"t"},{"boundingBox":{"vertices":[{"x":1377,"y":1409},{"x":1407,"y":1410},{"x":1406,"y":1453},{"x":1376,"y":1452}]},"confidence":0.7487931,"text":"u"},{"boundingBox":{"vertices":[{"x":1405,"y":1410},{"x":1433,"y":1411},{"x":1432,"y":1454},{"x":1404,"y":1453}]},"confidence":0.3783978,"property":{"detectedBreak":{"type":"LINE_BREAK"}},"text":"m"}]}]}]},{"blockType":"TEXT","boundingBox":{"vertices":[{"x":1477,"y":215},{"x":2161,"y":223},{"x":2159,"y":425},{"x":1475,"y":417}]},"confidence":0.9794398,"paragraphs":[{"boundingBox":{"vertices":[{"x":1477,"y":215},{"x":2161,"y":223},{"x":2159,"y":425},{"x":1475,"y":417}]},"confidence":0.9794398,"words":[{"boundingBox":{"vertices":[{"x":1478,"y":216},{"x":1741,"y":221},{"x":1740,"y":299},{"x":1477,"y":294}]},"confidence":0.9199529,"property":{"detectedLanguages":[{"confidence":1,"languageCode":"hi"}]},"symbols":[{"boundingBox":{"vertices":[{"x":1478,"y":216},{"x":1602,"y":218},{"x":1601,"y":296},{"x":1477,"y":294}]},"confidence":0.7737224,"text":"\u092d\u093e"},{"boundingBox":{"vertices":[{"x":1592,"y":218},{"x":1661,"y":219},{"x":1660,"y":297},{"x":1591,"y":296}]},"confidence":0.9909691,"text":"\u0930"},{"boundingBox":{"vertices":[{"x":1649,"y":219},{"x":1741,"y":221},{"x":1740,"y":299},{"x":1648,"y":297}]},"confidence":0.9951673,"property":{"detectedBreak":{"type":"SPACE"}},"text":"\u0924"}]},{"boundingBox":{"vertices":[{"x":1821,"y":221},{"x":2157,"y":227},{"x":2155,"y":306},{"x":1820,"y":300}]},"confidence":0.98674893,"property":{"detectedLanguages":[{"confidence":1,"languageCode":"hi"}]},"symbols":[{"boundingBox":{"vertices":[{"x":1821,"y":222},{"x":1911,"y":224},{"x":1910,"y":302},{"x":1820,"y":300}]},"confidence":0.9931347,"text":"\u0938"},{"boundingBox":{"vertices":[{"x":1909,"y":223},{"x":1972,"y":224},{"x":1971,"y":302},{"x":1908,"y":301}]},"confidence":0.9925779,"text":"\u0930"},{"boundingBox":{"vertices":[{"x":1967,"y":225},{"x":2093,"y":227},{"x":2092,"y":305},{"x":1966,"y":303}]},"confidence":0.9783629,"text":"\u0915\u093e"},{"boundingBox":{"vertices":[{"x":2088,"y":227},{"x":2157,"y":228},{"x":2156,"y":306},{"x":2087,"y":305}]},"confidence":0.9829201,"property":{"detectedBreak":{"type":"EOL_SURE_SPACE"}},"text":"\u0930"}]},{"boundingBox":{"vertices":[{"x":1488,"y":346},{"x":1723,"y":347},{"x":1723,"y":418},{"x":1488,"y":417}]},"confidence":0.99252284,"property":{"detectedLanguages":[{"confidence":1,"languageCode":"en"}]},"symbols":[{"boundingBox":{"vertices":[{"x":1488,"y":347},{"x":1540,"y":347},{"x":1540,"y":417},{"x":1488,"y":417}]},"confidence":0.9928842,"text":"G"},{"boundingBox":{"vertices":[{"x":1549,"y":347},{"x":1601,"y":347},{"x":1601,"y":417},{"x":1549,"y":417}]},"confidence":0.9926391,"text":"O"},{"boundingBox":{"vertices":[{"x":1601,"y":347},{"x":1673,"y":347},{"x":1673,"y":417},{"x":1601,"y":417}]},"confidence":0.992419,"text":"V"},{"boundingBox":{"vertices":[{"x":1661,"y":347},{"x":1723,"y":347},{"x":1723,"y":417},{"x":1661,"y":417}]},"confidence":0.99214894,"text":"T"}]},{"boundingBox":{"vertices":[{"x":1722,"y":348},{"x":1738,"y":348},{"x":1738,"y":418},{"x":1722,"y":418}]},"confidence":0.98877364,"property":{"detectedLanguages":[{"confidence":1,"languageCode":"en"}]},"symbols":[{"boundingBox":{"vertices":[{"x":1722,"y":348},{"x":1738,"y":348},{"x":1738,"y":418},{"x":1722,"y":418}]},"confidence":0.98877364,"property":{"detectedBreak":{"type":"SPACE"}},"text":"."}]},{"boundingBox":{"vertices":[{"x":1766,"y":348},{"x":1878,"y":349},{"x":1878,"y":419},{"x":1766,"y":418}]},"confidence":0.99343264,"property":{"detectedLanguages":[{"confidence":1,"languageCode":"en"}]},"symbols":[{"boundingBox":{"vertices":[{"x":1766,"y":348},{"x":1815,"y":348},{"x":1815,"y":418},{"x":1766,"y":418}]},"confidence":0.9916881,"text":"O"},{"boundingBox":{"vertices":[{"x":1834,"y":348},{"x":1878,"y":348},{"x":1878,"y":418},{"x":1834,"y":418}]},"confidence":0.9951772,"property":{"detectedBreak":{"type":"SPACE"}},"text":"F"}]},{"boundingBox":{"vertices":[{"x":1904,"y":348},{"x":2159,"y":349},{"x":2159,"y":420},{"x":1904,"y":419}]},"confidence":0.9913542,"property":{"detectedLanguages":[{"confidence":1,"languageCode":"en"}]},"symbols":[{"boundingBox":{"vertices":[{"x":1904,"y":349},{"x":1927,"y":349},{"x":1927,"y":419},{"x":1904,"y":419}]},"confidence":0.9928788,"text":"I"},{"boundingBox":{"vertices":[{"x":1943,"y":349},{"x":1997,"y":349},{"x":1997,"y":419},{"x":1943,"y":419}]},"confidence":0.9962186,"text":"N"},{"boundingBox":{"vertices":[{"x":1998,"y":349},{"x":2060,"y":349},{"x":2060,"y":419},{"x":1998,"y":419}]},"confidence":0.99504954,"text":"D"},{"boundingBox":{"vertices":[{"x":2064,"y":350},{"x":2092,"y":350},{"x":2092,"y":420},{"x":2064,"y":420}]},"confidence":0.9898821,"text":"I"},{"boundingBox":{"vertices":[{"x":2095,"y":350},{"x":2159,"y":350},{"x":2159,"y":420},{"x":2095,"y":420}]},"confidence":0.98274195,"property":{"detectedBreak":{"type":"LINE_BREAK"}},"text":"A"}]}]}]}],"confidence":0.85509527,"height":1653,"property":{"detectedLanguages":[{"confidence":0.43759173,"languageCode":"en"},{"confidence":0.23228823,"languageCode":"hi"},{"confidence":0.044707693,"languageCode":"la"},{"confidence":0.04223623,"languageCode":"mr"}]},"width":2339}],"text":"\u0906\u092f\u0915\u0930 \u0935\u093f\u092d\u093e\u0917\nINCOME TAX DEPARTMENT\n\u0938\u094d\u0925\u093e\u092f\u0940 \u0932\u0947\u0916\u093e \u0938\u0902\u0916\u094d\u092f\u093e \u0915\u093e\u0930\u094d\u0921\nPermanent Account Number Card\nEXHPD6846P\nRant / Name\nDIPANKAR DHAURIA\n\u092a\u093f\u0924\u093e \u0915\u093e \u0928\u093e\u092e | Father's Name\nPURNENDU DHAURIA\n\u091c\u0928\u094d\u092e \u0915\u0940 \u0924\u093e\u0930\u0940\u0916 / Date of\n27/11/1996\nET/Signatum\n\u092d\u093e\u0930\u0924 \u0938\u0930\u0915\u093e\u0930\nGOVT. OF INDIA"},"textAnnotations":[{"boundingPoly":{"vertices":[{"x":183,"y":166},{"x":2161,"y":166},{"x":2161,"y":1454},{"x":183,"y":1454}]},"description":"\u0906\u092f\u0915\u0930 \u0935\u093f\u092d\u093e\u0917\nINCOME TAX DEPARTMENT\n\u0938\u094d\u0925\u093e\u092f\u0940 \u0932\u0947\u0916\u093e \u0938\u0902\u0916\u094d\u092f\u093e \u0915\u093e\u0930\u094d\u0921\nPermanent Account Number Card\nEXHPD6846P\nRant / Name\nDIPANKAR DHAURIA\n\u092a\u093f\u0924\u093e \u0915\u093e \u0928\u093e\u092e | Father's Name\nPURNENDU DHAURIA\n\u091c\u0928\u094d\u092e \u0915\u0940 \u0924\u093e\u0930\u0940\u0916 / Date of\n27/11/1996\nET/Signatum\n\u092d\u093e\u0930\u0924 \u0938\u0930\u0915\u093e\u0930\nGOVT. OF INDIA","locale":"en"},{"boundingPoly":{"vertices":[{"x":241,"y":169},{"x":651,"y":173},{"x":650,"y":275},{"x":240,"y":271}]},"description":"\u0906\u092f\u0915\u0930"},{"boundingPoly":{"vertices":[{"x":726,"y":175},{"x":1048,"y":178},{"x":1047,"y":279},{"x":725,"y":276}]},"description":"\u0935\u093f\u092d\u093e\u0917"},{"boundingPoly":{"vertices":[{"x":231,"y":328},{"x":478,"y":332},{"x":477,"y":405},{"x":230,"y":401}]},"description":"INCOME"},{"boundingPoly":{"vertices":[{"x":493,"y":332},{"x":607,"y":334},{"x":606,"y":407},{"x":492,"y":405}]},"description":"TAX"},{"boundingPoly":{"vertices":[{"x":627,"y":335},{"x":1047,"y":342},{"x":1046,"y":415},{"x":626,"y":408}]},"description":"DEPARTMENT"},{"boundingPoly":{"vertices":[{"x":740,"y":489},{"x":910,"y":491},{"x":909,"y":559},{"x":739,"y":557}]},"description":"\u0938\u094d\u0925\u093e\u092f\u0940"},{"boundingPoly":{"vertices":[{"x":922,"y":491},{"x":1056,"y":493},{"x":1055,"y":561},{"x":921,"y":559}]},"description":"\u0932\u0947\u0916\u093e"},{"boundingPoly":{"vertices":[{"x":1078,"y":493},{"x":1225,"y":495},{"x":1224,"y":563},{"x":1077,"y":561}]},"description":"\u0938\u0902\u0916\u094d\u092f\u093e"},{"boundingPoly":{"vertices":[{"x":1243,"y":495},{"x":1365,"y":497},{"x":1364,"y":565},{"x":1242,"y":563}]},"description":"\u0915\u093e\u0930\u094d\u0921"},{"boundingPoly":{"vertices":[{"x":633,"y":576},{"x":909,"y":579},{"x":909,"y":629},{"x":633,"y":626}]},"description":"Permanent"},{"boundingPoly":{"vertices":[{"x":917,"y":579},{"x":1129,"y":581},{"x":1129,"y":631},{"x":917,"y":629}]},"description":"Account"},{"boundingPoly":{"vertices":[{"x":1141,"y":581},{"x":1342,"y":583},{"x":1342,"y":633},{"x":1141,"y":631}]},"description":"Number"},{"boundingPoly":{"vertices":[{"x":1353,"y":583},{"x":1473,"y":584},{"x":1473,"y":634},{"x":1353,"y":633}]},"description":"Card"},{"boundingPoly":{"vertices":[{"x":842,"y":686},{"x":1324,"y":689},{"x":1324,"y":745},{"x":842,"y":742}]},"description":"EXHPD6846P"},{"boundingPoly":{"vertices":[{"x":205,"y":825},{"x":313,"y":826},{"x":313,"y":872},{"x":205,"y":871}]},"description":"Rant"},{"boundingPoly":{"vertices":[{"x":306,"y":827},{"x":338,"y":827},{"x":338,"y":872},{"x":306,"y":872}]},"description":"/"},{"boundingPoly":{"vertices":[{"x":337,"y":826},{"x":468,"y":827},{"x":468,"y":873},{"x":337,"y":872}]},"description":"Name"},{"boundingPoly":{"vertices":[{"x":222,"y":895},{"x":528,"y":898},{"x":528,"y":944},{"x":222,"y":941}]},"description":"DIPANKAR"},{"boundingPoly":{"vertices":[{"x":548,"y":898},{"x":821,"y":900},{"x":821,"y":946},{"x":548,"y":944}]},"description":"DHAURIA"},{"boundingPoly":{"vertices":[{"x":206,"y":1044},{"x":301,"y":1046},{"x":300,"y":1096},{"x":205,"y":1094}]},"description":"\u092a\u093f\u0924\u093e"},{"boundingPoly":{"vertices":[{"x":314,"y":1046},{"x":371,"y":1047},{"x":370,"y":1096},{"x":313,"y":1095}]},"description":"\u0915\u093e"},{"boundingPoly":{"vertices":[{"x":391,"y":1048},{"x":469,"y":1049},{"x":468,"y":1098},{"x":390,"y":1097}]},"description":"\u0928\u093e\u092e"},{"boundingPoly":{"vertices":[{"x":504,"y":1050},{"x":510,"y":1050},{"x":509,"y":1099},{"x":503,"y":1099}]},"description":"|"},{"boundingPoly":{"vertices":[{"x":527,"y":1050},{"x":699,"y":1053},{"x":698,"y":1103},{"x":526,"y":1100}]},"description":"Father's"},{"boundingPoly":{"vertices":[{"x":719,"y":1053},{"x":836,"y":1055},{"x":835,"y":1104},{"x":718,"y":1102}]},"description":"Name"},{"boundingPoly":{"vertices":[{"x":217,"y":1120},{"x":550,"y":1123},{"x":550,"y":1167},{"x":217,"y":1164}]},"description":"PURNENDU"},{"boundingPoly":{"vertices":[{"x":571,"y":1123},{"x":848,"y":1126},{"x":848,"y":1170},{"x":571,"y":1167}]},"description":"DHAURIA"},{"boundingPoly":{"vertices":[{"x":186,"y":1303},{"x":287,"y":1305},{"x":286,"y":1358},{"x":185,"y":1356}]},"description":"\u091c\u0928\u094d\u092e"},{"boundingPoly":{"vertices":[{"x":299,"y":1305},{"x":363,"y":1306},{"x":362,"y":1359},{"x":298,"y":1358}]},"description":"\u0915\u0940"},{"boundingPoly":{"vertices":[{"x":376,"y":1307},{"x":508,"y":1310},{"x":507,"y":1363},{"x":375,"y":1360}]},"description":"\u0924\u093e\u0930\u0940\u0916"},{"boundingPoly":{"vertices":[{"x":533,"y":1310},{"x":545,"y":1310},{"x":544,"y":1363},{"x":532,"y":1363}]},"description":"/"},{"boundingPoly":{"vertices":[{"x":557,"y":1310},{"x":665,"y":1312},{"x":664,"y":1366},{"x":556,"y":1364}]},"description":"Date"},{"boundingPoly":{"vertices":[{"x":652,"y":1313},{"x":730,"y":1315},{"x":729,"y":1368},{"x":651,"y":1366}]},"description":"of"},{"boundingPoly":{"vertices":[{"x":202,"y":1387},{"x":594,"y":1387},{"x":594,"y":1443},{"x":202,"y":1443}]},"description":"27/11/1996"},{"boundingPoly":{"vertices":[{"x":1125,"y":1401},{"x":1199,"y":1403},{"x":1198,"y":1446},{"x":1124,"y":1444}]},"description":"ET"},{"boundingPoly":{"vertices":[{"x":1212,"y":1403},{"x":1239,"y":1404},{"x":1238,"y":1447},{"x":1211,"y":1446}]},"description":"/"},{"boundingPoly":{"vertices":[{"x":1233,"y":1404},{"x":1433,"y":1411},{"x":1431,"y":1454},{"x":1232,"y":1447}]},"description":"Signatum"},{"boundingPoly":{"vertices":[{"x":1478,"y":216},{"x":1741,"y":221},{"x":1740,"y":299},{"x":1477,"y":294}]},"description":"\u092d\u093e\u0930\u0924"},{"boundingPoly":{"vertices":[{"x":1821,"y":221},{"x":2157,"y":227},{"x":2155,"y":306},{"x":1820,"y":300}]},"description":"\u0938\u0930\u0915\u093e\u0930"},{"boundingPoly":{"vertices":[{"x":1488,"y":346},{"x":1723,"y":347},{"x":1723,"y":418},{"x":1488,"y":417}]},"description":"GOVT"},{"boundingPoly":{"vertices":[{"x":1722,"y":348},{"x":1738,"y":348},{"x":1738,"y":418},{"x":1722,"y":418}]},"description":"."},{"boundingPoly":{"vertices":[{"x":1766,"y":348},{"x":1878,"y":349},{"x":1878,"y":419},{"x":1766,"y":418}]},"description":"OF"},{"boundingPoly":{"vertices":[{"x":1904,"y":348},{"x":2159,"y":349},{"x":2159,"y":420},{"x":1904,"y":419}]},"description":"INDIA"}]}]},"Page":1}],"statusCode":200,"txnId":"TXN0000001--102738"}
